setup.py
aspose_imaging_java_for_jython.egg-info/PKG-INFO
aspose_imaging_java_for_jython.egg-info/SOURCES.txt
aspose_imaging_java_for_jython.egg-info/dependency_links.txt
aspose_imaging_java_for_jython.egg-info/top_level.txt
asposeimaging/__init__.py