Metadata-Version: 1.1
Name: aspose-imaging-java-for-jython
Version: 1.0
Summary: Aspose.Imaging Java for Jython is a project that demonstrates / provides the Aspose.Imaging for Java API usage examples in Jython.
Home-page: http://www.aspose.com/docs/display/imagingjava/Aspose.Imaging+Java+for+Jython
Author: Fahad Adeel
Author-email: imaging@aspose.com
License: UNKNOWN
Platform: UNKNOWN
Classifier: Programming Language :: Python
Classifier: Programming Language :: Python :: 2
Classifier: License :: OSI Approved :: MIT License
Classifier: Operating System :: OS Independent
